Workbook

Sheet 📊 Painel Geral
A1: INTIMIDADE — Estudo de Viabilidade Financeira
A3: ⚙️ ENTRADAS — EDITE AQUI | D3: 📦 CUSTO DO KIT
A4: Preço de Venda (R$) | B4: 249 | D4: Óleo de Massagem | E4: 35
A5: Unidades Vendidas / Mês | B5: 20 | D5: Vela Aromática | E5: 28
A6: Taxa Plataforma (%) | B6: 16 | D6: Máscara Tapa-olhos | E6: 20
A7: Taxa Pagamento (%) | B7: 4.99 | D7: Embalagem Premium | E7: 18
A8: Frete Pago pelo Vendedor (R$) | B8: 22 | D8: Fita / Laço / Adesivo | E8: 5
A9: Custo Fixo Mensal (R$) | B9: 800 | D9: Mão de Obra (Montagem) | E9: 10
A10: Marketing Mensal (R$) | B10: 400 | D10: Material de Proteção | E10: 4
A11: Alíquota Imposto (%) | B11: 5.07 | D11: TOTAL CUSTO / KIT | E11: =SUM(E4:E10)
A14: 📈 RESULTADOS CALCULADOS
A15: Receita Bruta | B15: =B4*B5
A16: (-) Custo Variável Total | B16: =E11*B5
A17: (-) Taxa Plataforma | B17: =B4*(B6/100)*B5
A18: (-) Taxa Pagamento | B18: =B4*(B7/100)*B5
A19: (-) Frete Total | B19: =B8*B5
A20: (-) Custos Fixos + Marketing | B20: =B9+B10
A21: (-) Impostos | B21: =B4*B5*(B11/100)
A23: LUCRO LÍQUIDO / MÊS | B23: =B15-B16-B17-B18-B19-B20-B21
A24: MARGEM LÍQUIDA (%) | B24: =IF(B15>0,(B23/B15)*100,0)
A25: LUCRO POR KIT | B25: =B23/B5

Sheet 🎯 Cenários
A1: INTIMIDADE — Cenários de Vendas
A3: Cenário | B3: Unidades/Mês | C3: Receita Bruta | D3: Lucro Mensal | E3: Margem (%) | F3: Viabilidade
A4: Pessimista | B4: =ROUND('📊 Painel Geral'!B5*0.5,0) | C4: ='📊 Painel Geral'!B4*B4 | D4: =C4-('📊 Painel Geral'!E11*B4)-(('📊 Painel Geral'!B4*('📊 Painel Geral'!B6+'📊 Painel Geral'!B7)/100)+'📊 Painel Geral'!B8*B4)-('📊 Painel Geral'!B4*('📊 Painel Geral'!B11/100)*B4)-('📊 Painel Geral'!B9+'📊 Painel Geral'!B10) | E4: =IF(C4>0,D4/C4*100,0) | F4: =IF(E4>25,"✅ Viável",IF(E4>10,"⚠️ Marginal","❌ Inviável"))
A5: Realista | B5: =ROUND('📊 Painel Geral'!B5*1.0,0) | C5: ='📊 Painel Geral'!B4*B5 | D5: =C5-('📊 Painel Geral'!E11*B5)-(('📊 Painel Geral'!B4*('📊 Painel Geral'!B6+'📊 Painel Geral'!B7)/100)+'📊 Painel Geral'!B8*B5)-('📊 Painel Geral'!B4*('📊 Painel Geral'!B11/100)*B5)-('📊 Painel Geral'!B9+'📊 Painel Geral'!B10) | E5: =IF(C5>0,D5/C5*100,0) | F5: =IF(E5>25,"✅ Viável",IF(E5>10,"⚠️ Marginal","❌ Inviável"))
A6: Otimista | B6: =ROUND('📊 Painel Geral'!B5*1.5,0) | C6: ='📊 Painel Geral'!B4*B6 | D6: =C6-('📊 Painel Geral'!E11*B6)-(('📊 Painel Geral'!B4*('📊 Painel Geral'!B6+'📊 Painel Geral'!B7)/100)+'📊 Painel Geral'!B8*B6)-('📊 Painel Geral'!B4*('📊 Painel Geral'!B11/100)*B6)-('📊 Painel Geral'!B9+'📊 Painel Geral'!B10) | E6: =IF(C6>0,D6/C6*100,0) | F6: =IF(E6>25,"✅ Viável",IF(E6>10,"⚠️ Marginal","❌ Inviável"))
A7: Agressivo | B7: =ROUND('📊 Painel Geral'!B5*2.5,0) | C7: ='📊 Painel Geral'!B4*B7 | D7: =C7-('📊 Painel Geral'!E11*B7)-(('📊 Painel Geral'!B4*('📊 Painel Geral'!B6+'📊 Painel Geral'!B7)/100)+'📊 Painel Geral'!B8*B7)-('📊 Painel Geral'!B4*('📊 Painel Geral'!B11/100)*B7)-('📊 Painel Geral'!B9+'📊 Painel Geral'!B10) | E7: =IF(C7>0,D7/C7*100,0) | F7: =IF(E7>25,"✅ Viável",IF(E7>10,"⚠️ Marginal","❌ Inviável"))

Sheet 📈 Payback & ROI
A1: INTIMIDADE — Investimento Inicial & Payback
A3: 💰 INVESTIMENTO INICIAL
A4: Estoque Inicial (30 kits) | B4: =30*'📊 Painel Geral'!E11
A5: Domínio + Hospedagem | B5: 200
A6: Material Visual / Fotos | B6: 500
A7: Capital de Giro Extra | B7: 300
A8: Outros | B8: 200
A9: TOTAL INVESTIMENTO | B9: =SUM(B4:B8)
A11: 📊 ANÁLISE DE RETORNO
A12: Lucro Mensal Esperado | B12: '📊 Painel Geral'!B23
A13: Margem Líquida | B13: '📊 Painel Geral'!B24
A14: Lucro por Kit | B14: '📊 Painel Geral'!B25
A15: Break-Even (unid./mês) | B15: =('📊 Painel Geral'!B9+'📊 Painel Geral'!B10)/MAX('📊 Painel Geral'!B25,0.01)
A16: Payback (meses) | B16: =IF('📊 Painel Geral'!B23>0,B9/'📊 Painel Geral'!B23,999)
A17: ROI Anual (%) | B17: =IF(B9>0,('📊 Painel Geral'!B23*12/B9)*100,0)
A18: Lucro Anual Estimado | B18: ='📊 Painel Geral'!B23*12

Sheet 📦 Kits & Produtos
A1: INTIMIDADE — Catálogo de Produtos e Kits
A3: Produto | B3: Fornecedor/Distribuidor | C3: Custo Unit. (R$) | D3: Incluso no Kit
A4: Óleo de Massagem 100ml | B4: Fornecedor A - Atacado | C4: 35 | D4: ✅
A5: Vela Aromática Soja | B5: Fornecedor A - Atacado | C5: 28 | D5: ✅
A6: Máscara Tapa-olhos Cetim | B6: Fornecedor B - Importado | C6: 20 | D6: ✅
A7: Embalagem Premium Black | B7: Gráfica Local | C7: 18 | D7: ✅
A8: Fita de Cetim + Adesivo | B8: Papelaria Atacado | C8: 5 | D8: ✅
A9: Pétala de Rosa Seca | B9: Flora Atacado | C9: 8 | D9: ⭕ Opcional
A10: Cartão Personalizado | B10: Gráfica Local | C10: 4 | D10: ⭕ Opcional
A11: Sachê Perfumado | B11: Fornecedor B - Importado | C11: 12 | D11: ⭕ Opcional

Sheet 🏛️ Impostos & Taxas
A1: INTIMIDADE — Guia de Impostos e Taxas de Marketplace
A3: Regime Tributário
A4: MEI | B4: ~R$ 75/mês fixo | C4: CNPJ simples. Limite R$81k/ano. Ideal para início.
A5: Simples Nacional - Anexo I (Comércio) | B5: 4% a 11,2% | C5: Sobre faturamento. Recomendado a partir de R$7k/mês.
A6: Lucro Presumido | B6: ~8% + 3% = ~11% | C6: Para faturamento acima de R$360k/ano.
A9: Taxas por Plataforma
A10: Mercado Livre - Clássico | B10: 10-11% + 4,99% pgto | C10: Visibilidade menor. Sem frete grátis obrigatório.
A11: Mercado Livre - Premium | B11: 16-19% + 4,99% pgto | C11: Topo de busca. Frete grátis obrigatório acima R$79.
A12: Shopee | B12: 12-16% | C12: Frete subsidiado em campanhas. Sem taxa de pgto extra.
A13: WhatsApp / Site Próprio | B13: 0% + 3,5% gateway | C13: Melhor margem. Você gerencia o atendimento.
A14: Amazon BR | B14: ~15% | C14: Marketplace premium. Exige cadastro como profissional.
